aparavi_dtc_sdk/__init__.py
aparavi_dtc_sdk/client.py
aparavi_dtc_sdk/exceptions.py
aparavi_dtc_sdk/models.py
aparavi_dtc_sdk/pipelines/advanced_parser.json
aparavi_dtc_sdk/pipelines/audio_and_summary.json
aparavi_dtc_sdk/pipelines/simple_audio_transcribe.json
aparavi_dtc_sdk/pipelines/simple_parser.json
tests/__init__.py
tests/test_client.py
aparavi_dtc_sdk-1.1.1.dist-info/METADATA
aparavi_dtc_sdk-1.1.1.dist-info/WHEEL
aparavi_dtc_sdk-1.1.1.dist-info/top_level.txt
aparavi_dtc_sdk-1.1.1.dist-info/RECORD
