Metadata-Version: 2.4
Name: aparavi-dtc-sdk
Version: 1.1.1
Summary: Python SDK for Aparavi Data Toolchain API
Home-page: https://dtc.aparavi.com
Author: Aparavi
Author-email: support@aparavi.com
Project-URL: Bug Reports, https://github.com/AparaviSoftware/aparavi-dtc-sdk/issues
Project-URL: Source, https://github.com/AparaviSoftware/aparavi-dtc-sdk
Keywords: aparavi dtc data toolchain api sdk web services
Classifier: Development Status :: 4 - Beta
Classifier: Intended Audience :: Developers
Classifier: License :: OSI Approved :: MIT License
Classifier: Operating System :: OS Independent
Classifier: Programming Language :: Python :: 3
Classifier: Programming Language :: Python :: 3.8
Classifier: Programming Language :: Python :: 3.9
Classifier: Programming Language :: Python :: 3.10
Classifier: Programming Language :: Python :: 3.11
Classifier: Programming Language :: Python :: 3.12
Requires-Python: >=3.8
Provides-Extra: dev
Requires-Dist: pytest>=7.0.0; extra == "dev"
Requires-Dist: pytest-cov>=4.0.0; extra == "dev"
Requires-Dist: black>=22.0.0; extra == "dev"
Requires-Dist: flake8>=4.0.0; extra == "dev"
Requires-Dist: mypy>=0.991; extra == "dev"
Dynamic: author
Dynamic: author-email
Dynamic: classifier
Dynamic: description
Dynamic: description-content-type
Dynamic: home-page
Dynamic: keywords
Dynamic: project-url
Dynamic: provides-extra
Dynamic: requires-python
Dynamic: summary
